{"directed": true, "multigraph": false, "graph": {"node_default": {}, "edge_default": {}, "DateObtained": "19/10/10", "GeoLocation": "USA, Europe", "GeoExtent": "Country+", "Network": "Cogent ", "Provenance": "Primary", "Note": "Contains Aleron", "Source": "http://www.cogentco.com/us/network_map.php", "Version": "1.0", "DateType": "Current", "Type": "COM", "Backbone": 1, "Commercial": 0, "label": "Cogentco", "ToolsetVersion": "0.3.34dev-20120328", "Customer": 1, "IX": 0, "SourceGitVersion": "e278b1b", "DateModifier": "=", "DateMonth": "08", "LastAccess": "3/08/10", "Access": 0, "Layer": "IP", "Creator": "Topology Zoo Toolset", "Developed": 1, "Transit": 1, "NetworkDate": "2010_08", "DateYear": "2010", "LastProcessed": "2011_09_01", "Testbed": 0}, "nodes": [{"hyperedge": 1, "Internal": 1, "label": "None", "id": 144}, {"Internal": 1, "Latitude": 36.16589, "Country": "United States", "type": "On-Net and Off-Net Market", "Longitude": -86.78444, "label": "Nashville", "id": 19}, {"hyperedge": 1, "Internal": 1, "label": "None", "id": 149}, {"hyperedge": 1, "Internal": 1, "label": "None", "id": 150}, {"Internal": 1, "Latitude": 29.95465, "Country": "United States", "type": "On-Net and Off-Net Market with Cogent Data Center(s)", "Longitude": -90.07507, "label": "New Orleans", "id": 62}, {"Internal": 1, "Latitude": 32.29876, "Country": "United States", "type": "On-Net and Off-Net Market", "Longitude": -90.18481, "label": "Jackson", "id": 63}, {"Internal": 1, "Latitude": 36.15398, "Country": "United States", "type": "On-Net and Off-Net Market", "Longitude": -95.99278, "label": "Tulsa", "id": 64}, {"Internal": 1, "Latitude": 35.46756, "Country": "United States", "type": "On-Net and Off-Net Market", "Longitude": -97.51643, "label": "Oklahoma City", "id": 65}, {"Internal": 1, "Latitude": 32.72541, "Country": "United States", "type": "On-Net and Off-Net Market", "Longitude": -97.32085, "label": "Fort Worth", "id": 66}, {"Internal": 1, "Latitude": 32.78306, "Country": "United States", "type": "On-Net and Off-Net Market with Cogent Data Center(s)", "Longitude": -96.80667, "label": "Dallas", "id": 67}, {"Internal": 1, "Latitude": 35.14953, "Country": "United States", "type": "On-Net and Off-Net Market", "Longitude": -90.04898, "label": "Memphis", "id": 68}, {"Internal": 1, "Latitude": 29.76328, "Country": "United States", "type": "On-Net and Off-Net Market with Cogent Data Center(s)", "Longitude": -95.36327, "label": "Houston", "id": 69}, {"Internal": 1, "Latitude": 25.77427, "Country": "United States", "type": "On-Net and Off-Net Market with Cogent Data Center(s)", "Longitude": -80.19366, "label": "Miami", "id": 80}, {"Internal": 1, "Latitude": 26.35869, "Country": "United States", "type": "On-Net and Off-Net Market with Cogent Data Center(s)", "Longitude": -80.0831, "label": "Boca Raton", "id": 81}, {"Internal": 1, "Latitude": 33.749, "Country": "United States", "type": "On-Net and Off-Net Market with Cogent Data Center(s)", "Longitude": -84.38798, "label": "Atlanta", "id": 82}, {"Internal": 1, "Latitude": 35.22709, "Country": "United States", "type": "On-Net and Off-Net Market", "Longitude": -80.84313, "label": "Charlotte", "id": 83}, {"Internal": 1, "Latitude": 27.94752, "Country": "United States", "type": "On-Net and Off-Net Market", "Longitude": -82.45843, "label": "Tampa", "id": 86}, {"Internal": 1, "Latitude": 28.53834, "Country": "United States", "type": "On-Net and Off-Net Market", "Longitude": -81.37924, "label": "Orlando", "id": 87}, {"Internal": 1, "Latitude": 30.33218, "Country": "United States", "type": "On-Net and Off-Net Market", "Longitude": -81.65565, "label": "Jacksonville", "id": 88}, {"geocode_append": "US", "Country": "United States", "Longitude": -86.80249, "label": "Birmingham", "Internal": 1, "Latitude": 33.52066, "type": "On-Net and Off-Net Market", "id": 89}], "links": [{"id": "e204", "key": 0, "capacity": 200, "source": 144, "target": 62}, {"id": "e214", "key": 0, "capacity": 200, "source": 144, "target": 69}, {"id": "e244", "key": 0, "capacity": 200, "source": 144, "target": 149}, {"id": "e187", "key": 0, "capacity": 200, "source": 19, "target": 89}, {"id": "e188", "key": 0, "capacity": 200, "source": 19, "target": 68}, {"id": "e189", "key": 0, "capacity": 200, "source": 19, "target": 82}, {"id": "e206", "key": 0, "capacity": 200, "source": 149, "target": 63}, {"id": "e244", "key": 0, "capacity": 200, "source": 149, "target": 144}, {"id": "e243", "key": 0, "capacity": 200, "source": 149, "target": 150}, {"id": "e195", "key": 0, "capacity": 200, "source": 150, "target": 82}, {"id": "e196", "key": 0, "capacity": 200, "source": 150, "target": 89}, {"id": "e243", "key": 0, "capacity": 200, "source": 150, "target": 149}, {"id": "e204", "key": 0, "capacity": 200, "source": 62, "target": 144}, {"id": "e201", "key": 0, "capacity": 200, "source": 62, "target": 86}, {"id": "e205", "key": 0, "capacity": 200, "source": 62, "target": 63}, {"id": "e205", "key": 0, "capacity": 200, "source": 63, "target": 62}, {"id": "e207", "key": 0, "capacity": 200, "source": 63, "target": 68}, {"id": "e206", "key": 0, "capacity": 200, "source": 63, "target": 149}, {"id": "e208", "key": 0, "capacity": 200, "source": 64, "target": 65}, {"id": "e209", "key": 0, "capacity": 200, "source": 64, "target": 67}, {"id": "e210", "key": 0, "capacity": 200, "source": 64, "target": 68}, {"id": "e208", "key": 0, "capacity": 200, "source": 65, "target": 64}, {"id": "e211", "key": 0, "capacity": 200, "source": 65, "target": 66}, {"id": "e211", "key": 0, "capacity": 200, "source": 66, "target": 65}, {"id": "e212", "key": 0, "capacity": 200, "source": 66, "target": 67}, {"id": "e209", "key": 0, "capacity": 200, "source": 67, "target": 64}, {"id": "e212", "key": 0, "capacity": 200, "source": 67, "target": 66}, {"id": "e213", "key": 0, "capacity": 200, "source": 67, "target": 69}, {"id": "e188", "key": 0, "capacity": 200, "source": 68, "target": 19}, {"id": "e207", "key": 0, "capacity": 200, "source": 68, "target": 63}, {"id": "e210", "key": 0, "capacity": 200, "source": 68, "target": 64}, {"id": "e213", "key": 0, "capacity": 200, "source": 69, "target": 67}, {"id": "e214", "key": 0, "capacity": 200, "source": 69, "target": 144}, {"id": "e202", "key": 1, "capacity": 200, "source": 80, "target": 81}, {"id": "e200", "key": 0, "capacity": 200, "source": 80, "target": 86}, {"id": "e199", "key": 0, "capacity": 200, "source": 80, "target": 87}, {"id": "e202", "key": 1, "capacity": 200, "source": 81, "target": 80}, {"id": "e189", "key": 0, "capacity": 200, "source": 82, "target": 19}, {"id": "e194", "key": 0, "capacity": 200, "source": 82, "target": 88}, {"id": "e192", "key": 0, "capacity": 200, "source": 82, "target": 83}, {"id": "e195", "key": 0, "capacity": 200, "source": 82, "target": 150}, {"id": "e192", "key": 0, "capacity": 200, "source": 83, "target": 82}, {"id": "e201", "key": 0, "capacity": 200, "source": 86, "target": 62}, {"id": "e200", "key": 0, "capacity": 200, "source": 86, "target": 80}, {"id": "e198", "key": 0, "capacity": 200, "source": 86, "target": 87}, {"id": "e199", "key": 0, "capacity": 200, "source": 87, "target": 80}, {"id": "e198", "key": 0, "capacity": 200, "source": 87, "target": 86}, {"id": "e197", "key": 0, "capacity": 200, "source": 87, "target": 88}, {"id": "e194", "key": 0, "capacity": 200, "source": 88, "target": 82}, {"id": "e197", "key": 0, "capacity": 200, "source": 88, "target": 87}, {"id": "e187", "key": 0, "capacity": 200, "source": 89, "target": 19}, {"id": "e196", "key": 0, "capacity": 200, "source": 89, "target": 150}]}